MANIFEST.in
README.md
examples.ipynb
pyproject.toml
setup.cfg
setup.py
nfinder/__init__.py
nfinder/nfinder.py
nfinder/plotting.py
nfinder/util.py
nfinder.egg-info/PKG-INFO
nfinder.egg-info/SOURCES.txt
nfinder.egg-info/dependency_links.txt
nfinder.egg-info/entry_points.txt
nfinder.egg-info/top_level.txt
nfinder/plugins/__init__.py
nfinder/plugins/find.py
nfinder/plugins/napari.py
nfinder/test_images/__init__.py
nfinder/test_images/merge_c_elegans.tif
nfinder/test_images/merge_drosophila.tif
nfinder/test_images/segmentation_c_elegans.tif
nfinder/test_images/segmentation_drosophila.tif