Metadata-Version: 2.1
Name: nfinder
Version: 0.3
Summary: Automatic inference of neighboring cells based on their Delaunay triangulation.
Home-page: https://github.com/santi-rodriguez/nfinder
Author: Santiago N. Rodriguez Alvarez
Author-email: rodriguezsantiago96@gmail.com
License: UNKNOWN
Keywords: science,microscopy,image processing,cells neighbors
Platform: UNKNOWN
Classifier: Development Status :: 4 - Beta
Classifier: Programming Language :: Python :: 3.7
Classifier: License :: OSI Approved :: MIT License
Classifier: Operating System :: OS Independent
Classifier: Framework :: napari
Requires-Python: >=3.7
